predictive_model_support/__init__.py
predictive_model_support/create_predictive_model.py
predictive_model_support/model_vizualization.py
tarandm_predictive_model_support-0.0.2.dist-info/METADATA
tarandm_predictive_model_support-0.0.2.dist-info/WHEEL
tarandm_predictive_model_support-0.0.2.dist-info/RECORD
