Metadata-Version: 2.1
Name: tarandm-predictive-model-support
Version: 0.0.2
Summary: Package contains support functions for creating predictive models in format compatible with TaranDM software.
Author: Marek Teller
Author-email: mteller@taran.ai
Requires-Python: >=3.10,<3.11
Classifier: Programming Language :: Python :: 3
Classifier: Programming Language :: Python :: 3.10
Requires-Dist: aiohttp
Requires-Dist: llvmlite
Requires-Dist: matplotlib
Requires-Dist: numba (==0.56.4)
Requires-Dist: pandas
Requires-Dist: path
Requires-Dist: scikit-learn
Requires-Dist: shap
Requires-Dist: structlog
Requires-Dist: xgboost
